{
  "project_info": {
    "project_number": "330644594681",
    "project_id": "collegeapp-e02e4",
    "storage_bucket": "collegeapp-e02e4.appspot.com",
    "firebase_url": "https://collegeapp-e02e4-default-rtdb.firebaseio.com/"
  },
  "client": [
    {
      "client_info": {
        "mobilesdk_app_id": "1:330644594681:android:e41bf29835886e613a2728",
        "android_client_info": {
          "package_name": "com.example.college_01"
        }
      },
      "oauth_client": [
        {
          "client_id": "330644594681-85etql1jvg7n34fcc15f6gppubl56ek4.apps.googleusercontent.com",
          "client_type": 3
        }
      ],
      "api_key": [
        {
          "current_key": "AIzaSyDK_U-Qudw1R0szLcXd9BhGRLBUeEGHOCs"
        }
      ],
      "services": {
        "appinvite_service": {
          "other_platform_oauth_client": [
            {
              "client_id": "330644594681-85etql1jvg7n34fcc15f6gppubl56ek4.apps.googleusercontent.com",
              "client_type": 3
            }
          ]
        }
      }
    }
  ],
  "configuration_version": "1"
}